Metadata-Version: 2.1
Name: stitch3d
Version: 1.0.3
Summary: A computational method for tissue 3D reconstruction by joint modeling of multiple spatial transcriptomics slices.
Home-page: https://github.com/YangLabHKUST/STitch3D
Author: Gefei Wang
Author-email: gwangas@connect.ust.hk
License: MIT
Platform: UNKNOWN
Requires-Python: >=3.7
License-File: LICENSE
